{"ts":"2024-08-28T06:18:15.934Z","level":"error","error":{"originalError":{"name":"AccessTokenInvalid","message":"{\n  \"status\": 403,\n  \"statusText\": \"Forbidden\",\n  \"message\": \"The access token you sent could not be found or is invalid.\",\n  \"details\": {},\n  \"request\": {\n    \"url\": \"/spaces/vzrwykenux1p\",\n    \"headers\": {\n      \"Accept\": \"application/json, text/plain, */*\",\n      \"Content-Type\": \"application/vnd.contentful.management.v1+json\",\n      \"X-Contentful-User-Agent\": \"app contentful.import/0.0.0-determined-by-semantic-release; feature library-import; sdk contentful-management.js/11.31.9; platform node.js/v20.15.0; os Windows/v20.15.0;\",\n      \"CF-Sequence\": \"59b972b9-0fbe-4bdc-b9a1-205a20691c2c\",\n      \"Authorization\": \"Bearer ...Qrxvo\",\n      \"User-Agent\": \"axios/1.7.5\",\n      \"Accept-Encoding\": \"gzip, compress, deflate, br\"\n    },\n    \"method\": \"get\"\n  },\n  \"requestId\": \"de41619a-075d-482f-9544-58ce1ba35d44\"\n}"},"data":{"status":403,"statusText":"Forbidden","message":"The access token you sent could not be found or is invalid.","details":{},"request":{"url":"/spaces/vzrwykenux1p","headers":{"Accept":"application/json, text/plain, */*","Content-Type":"application/vnd.contentful.management.v1+json","X-Contentful-User-Agent":"app contentful.import/0.0.0-determined-by-semantic-release; feature library-import; sdk contentful-management.js/11.31.9; platform node.js/v20.15.0; os Windows/v20.15.0;","CF-Sequence":"59b972b9-0fbe-4bdc-b9a1-205a20691c2c","Authorization":"Bearer ...Qrxvo","User-Agent":"axios/1.7.5","Accept-Encoding":"gzip, compress, deflate, br"},"method":"get"},"requestId":"de41619a-075d-482f-9544-58ce1ba35d44"}}}